herzfeld/__init__.py
herzfeld-0.1.0.dist-info/licenses/LICENSE
herzfeld-0.1.0.dist-info/METADATA
herzfeld-0.1.0.dist-info/WHEEL
herzfeld-0.1.0.dist-info/top_level.txt
herzfeld-0.1.0.dist-info/RECORD
