Metadata-Version: 2.4
Name: herzfeld
Version: 0.1.0
Summary: High-fidelity Epigraphic Rendering for Zonated Feature Extraction and Labelled Datasets
Author-email: Andrea Marruzzo <amarruzzo@gmail.com>
License: MIT
Classifier: Programming Language :: Python :: 3
Classifier: License :: OSI Approved :: MIT License
Classifier: Operating System :: OS Independent
Classifier: Topic :: Scientific/Engineering :: Artificial Intelligence
Classifier: Topic :: Scientific/Engineering :: Image Recognition
Requires-Python: >=3.10
License-File: LICENSE
Requires-Dist: numpy
Requires-Dist: openexr
Dynamic: license-file
